[
  {
    "ContainingType": "Program\u002B\u003C\u003Ec",
    "Method": "\u003C\u003CMain\u003E$\u003Eb__0_2",
    "RelativePath": "Comment",
    "HttpMethod": "POST",
    "IsController": false,
    "Order": 0,
    "Parameters": [
      {
        "Name": "comment",
        "Type": "ForumFeedback.Application.Command.CommandDto.CreateCommentDto",
        "IsRequired": true
      }
    ],
    "ReturnTypes": [
      {
        "Type": "System.Void",
        "MediaTypes": [],
        "StatusCode": 200
      }
    ]
  },
  {
    "ContainingType": "Program\u002B\u003C\u003Ec",
    "Method": "\u003C\u003CMain\u003E$\u003Eb__0_3",
    "RelativePath": "Comment",
    "HttpMethod": "PUT",
    "IsController": false,
    "Order": 0,
    "Parameters": [
      {
        "Name": "comment",
        "Type": "ForumFeedback.Application.Command.CommandDto.UpdateCommentDto",
        "IsRequired": true
      }
    ],
    "ReturnTypes": [
      {
        "Type": "System.Void",
        "MediaTypes": [],
        "StatusCode": 200
      }
    ]
  },
  {
    "ContainingType": "Program\u002B\u003C\u003Ec",
    "Method": "\u003C\u003CMain\u003E$\u003Eb__0_0",
    "RelativePath": "Post",
    "HttpMethod": "POST",
    "IsController": false,
    "Order": 0,
    "Parameters": [
      {
        "Name": "post",
        "Type": "ForumFeedback.Application.Command.CommandDto.CreatePostDto",
        "IsRequired": true
      }
    ],
    "ReturnTypes": [
      {
        "Type": "System.Void",
        "MediaTypes": [],
        "StatusCode": 200
      }
    ]
  },
  {
    "ContainingType": "Program\u002B\u003C\u003Ec",
    "Method": "\u003C\u003CMain\u003E$\u003Eb__0_1",
    "RelativePath": "Post",
    "HttpMethod": "DELETE",
    "IsController": false,
    "Order": 0,
    "Parameters": [
      {
        "Name": "post",
        "Type": "ForumFeedback.Application.Command.CommandDto.DeleteDto",
        "IsRequired": true
      }
    ],
    "ReturnTypes": [
      {
        "Type": "System.Void",
        "MediaTypes": [],
        "StatusCode": 200
      }
    ]
  },
  {
    "ContainingType": "Program\u002B\u003C\u003Ec",
    "Method": "\u003C\u003CMain\u003E$\u003Eb__0_8",
    "RelativePath": "Post",
    "HttpMethod": "GET",
    "IsController": false,
    "Order": 0,
    "Parameters": [
      {
        "Name": "postId",
        "Type": "System.Int32",
        "IsRequired": true
      }
    ],
    "ReturnTypes": [
      {
        "Type": "System.Collections.Generic.IEnumerable\u00601[[ForumFeedback.Application.Queries.QueriesDto.PostDto, ForumFeedback.Application, Version=1.0.0.0, Culture=neutral, PublicKeyToken=null]]",
        "MediaTypes": [
          "application/json"
        ],
        "StatusCode": 200
      }
    ]
  },
  {
    "ContainingType": "Program\u002B\u003C\u003Ec",
    "Method": "\u003C\u003CMain\u003E$\u003Eb__0_7",
    "RelativePath": "Posts",
    "HttpMethod": "GET",
    "IsController": false,
    "Order": 0,
    "Parameters": [
      {
        "Name": "activityId",
        "Type": "System.Int32",
        "IsRequired": true
      }
    ],
    "ReturnTypes": [
      {
        "Type": "System.Collections.Generic.IEnumerable\u00601[[ForumFeedback.Application.Queries.QueriesDto.PostDto, ForumFeedback.Application, Version=1.0.0.0, Culture=neutral, PublicKeyToken=null]]",
        "MediaTypes": [
          "application/json"
        ],
        "StatusCode": 200
      }
    ]
  },
  {
    "ContainingType": "Program\u002B\u003C\u003Ec",
    "Method": "\u003C\u003CMain\u003E$\u003Eb__0_4",
    "RelativePath": "Vote",
    "HttpMethod": "POST",
    "IsController": false,
    "Order": 0,
    "Parameters": [
      {
        "Name": "vote",
        "Type": "ForumFeedback.Application.Command.CommandDto.CreateVoteDto",
        "IsRequired": true
      }
    ],
    "ReturnTypes": [
      {
        "Type": "System.Void",
        "MediaTypes": [],
        "StatusCode": 200
      }
    ]
  },
  {
    "ContainingType": "Program\u002B\u003C\u003Ec",
    "Method": "\u003C\u003CMain\u003E$\u003Eb__0_5",
    "RelativePath": "Vote",
    "HttpMethod": "PUT",
    "IsController": false,
    "Order": 0,
    "Parameters": [
      {
        "Name": "vote",
        "Type": "ForumFeedback.Application.Command.CommandDto.UpdateVoteDto",
        "IsRequired": true
      }
    ],
    "ReturnTypes": [
      {
        "Type": "System.Void",
        "MediaTypes": [],
        "StatusCode": 200
      }
    ]
  },
  {
    "ContainingType": "Program\u002B\u003C\u003Ec",
    "Method": "\u003C\u003CMain\u003E$\u003Eb__0_6",
    "RelativePath": "Vote",
    "HttpMethod": "DELETE",
    "IsController": false,
    "Order": 0,
    "Parameters": [
      {
        "Name": "vote",
        "Type": "ForumFeedback.Application.Command.CommandDto.DeleteVoteDto",
        "IsRequired": true
      }
    ],
    "ReturnTypes": [
      {
        "Type": "System.Void",
        "MediaTypes": [],
        "StatusCode": 200
      }
    ]
  }
]